{
    "type": "object",
    "properties": {
        "name": {
            "required": true,
            "type": "string"
        },
        "access_token": {
            "type": "string"
        },
        "alt": {
            "type": "string",
            "enum": [
                "json",
                "media",
                "proto"
            ],
            "default": "json"
        },
        "callback": {
            "type": "string"
        },
        "fields": {
            "type": "string"
        },
        "key": {
            "type": "string"
        },
        "oauth_token": {
            "type": "string"
        },
        "prettyPrint": {
            "type": "boolean",
            "default": true
        },
        "quotaUser": {
            "type": "string"
        },
        "uploadType": {
            "type": "string"
        },
        "upload_protocol": {
            "type": "string"
        },
        "requestBody": {
            "description": "A command.",
            "properties": {
                "createTime": {
                    "description": "The timestamp at which the command was created. The timestamp is automatically generated by the server.",
                    "format": "google-datetime",
                    "type": "string"
                },
                "duration": {
                    "description": "The duration for which the command is valid. The command will expire if not executed by the device during this time. The default duration if unspecified is ten minutes. There is no maximum duration.",
                    "format": "google-duration",
                    "type": "string"
                },
                "errorCode": {
                    "description": "If the command failed, an error code explaining the failure. This is not set when the command is cancelled by the caller.",
                    "enum": [
                        "COMMAND_ERROR_CODE_UNSPECIFIED",
                        "UNKNOWN",
                        "API_LEVEL",
                        "MANAGEMENT_MODE",
                        "INVALID_VALUE",
                        "UNSUPPORTED"
                    ],
                    "type": "string"
                },
                "newPassword": {
                    "description": "For commands of type RESET_PASSWORD, optionally specifies the new password.",
                    "type": "string"
                },
                "resetPasswordFlags": {
                    "description": "For commands of type RESET_PASSWORD, optionally specifies flags.",
                    "items": {
                        "enum": [
                            "RESET_PASSWORD_FLAG_UNSPECIFIED",
                            "REQUIRE_ENTRY",
                            "DO_NOT_ASK_CREDENTIALS_ON_BOOT",
                            "LOCK_NOW"
                        ],
                        "type": "string"
                    },
                    "type": "array"
                },
                "type": {
                    "description": "The type of the command.",
                    "enum": [
                        "COMMAND_TYPE_UNSPECIFIED",
                        "LOCK",
                        "RESET_PASSWORD",
                        "REBOOT"
                    ],
                    "type": "string"
                },
                "userName": {
                    "description": "The resource name of the user that owns the device in the form enterprises/{enterpriseId}/users/{userId}. This is automatically generated by the server based on the device the command is sent to.",
                    "type": "string"
                }
            },
            "type": "object"
        }
    }
}